[{"keyword": "海底捞淫秽视频案", "search_index": 516328, "index": 1}, {"keyword": "充气娃娃漏气报警", "search_index": 407252, "index": 2}, {"keyword": "王祖贤正面照曝光", "search_index": 280810, "index": 3}, {"keyword": "近期公布人口数据", "search_index": 230472, "index": 4}, {"keyword": "关之琳财产给弟弟", "search_index": 184086, "index": 5}, {"keyword": "南京加油站闪爆", "search_index": 173659, "index": 6}, {"keyword": "苍井空宣布怀孕", "search_index": 172812, "index": 7}, {"keyword": "月球背面全景图", "search_index": 156313, "index": 8}, {"keyword": "迪丽热巴年会表演", "search_index": 151483, "index": 9}, {"keyword": "张绍刚怼隐形爸爸", "search_index": 124654, "index": 10}, {"keyword": "中国游客泰国自杀", "search_index": 97337, "index": 11}, {"keyword": "北京政府迁址通州", "search_index": 74736, "index": 12}, {"keyword": "校长带学生跳鬼步", "search_index": 73725, "index": 13}, {"keyword": "千亿美元的离婚", "search_index": 73048, "index": 14}, {"keyword": "日本恢复记忆药", "search_index": 66058, "index": 15}, {"keyword": "杭州奔驰失控开庭", "search_index": 65900, "index": 16}, {"keyword": "奥斯卡取消主持人", "search_index": 65360, "index": 17}, {"keyword": "纽约带薪休假", "search_index": 64753, "index": 18}, {"keyword": "亚洲杯", "search_index": 61752, "index": 19}, {"keyword": "重庆男子遭家暴", "search_index": 55979, "index": 20}, {"keyword": "广州惠州楼房倒塌", "search_index": 53045, "index": 21}, {"keyword": "骑共享单车过年", "search_index": 47324, "index": 22}, {"keyword": "玉兔二号成功唤醒", "search_index": 47213, "index": 23}, {"keyword": "韩国的哥自杀", "search_index": 43968, "index": 24}, {"keyword": "特朗普不去达沃斯", "search_index": 42509, "index": 25}, {"keyword": "天鲲号完成测试", "search_index": 38943, "index": 26}, {"keyword": "马杜罗宣誓就职", "search_index": 38535, "index": 27}, {"keyword": "龙俊亨直播爆哭", "search_index": 37947, "index": 28}, {"keyword": "苏联末代主席去世", "search_index": 37863, "index": 29}, {"keyword": "日本猕猴走电线", "search_index": 37288, "index": 30}, {"keyword": "印度2亿人大罢工", "search_index": 37119, "index": 31}, {"keyword": "穆雷宣布退役", "search_index": 30727, "index": 32}, {"keyword": "江苏过期疫苗", "search_index": 29512, "index": 33}, {"keyword": "抢夺方向盘不缓刑", "search_index": 27952, "index": 34}, {"keyword": "梅威瑟炫耀手表", "search_index": 27567, "index": 35}, {"keyword": "商用量子计算机", "search_index": 25941, "index": 36}, {"keyword": "副校长出轨女生", "search_index": 25298, "index": 37}, {"keyword": "美政府停摆20天", "search_index": 23376, "index": 38}, {"keyword": "消防员替跑遭禁赛", "search_index": 22024, "index": 39}, {"keyword": "刘国梁回应张继科", "search_index": 20386, "index": 40}, {"keyword": "王思聪提名百大帅脸", "search_index": 20356, "index": 41}, {"keyword": "朱正廷自曝被催婚", "search_index": 20208, "index": 42}, {"keyword": "全国企业信用信息公示系统", "search_index": 18942, "index": 43}, {"keyword": "世界首富离婚内幕", "search_index": 17713, "index": 44}, {"keyword": "山口真帆道歉", "search_index": 17092, "index": 45}, {"keyword": "福原爱二胎孕肚照", "search_index": 16840, "index": 46}, {"keyword": "李沁粉丝开撕猫腻", "search_index": 16038, "index": 47}, {"keyword": "最低工资标准出炉", "search_index": 15856, "index": 48}, {"keyword": "声优户松遥结婚", "search_index": 14587, "index": 49}, {"keyword": "韩速滑名将遭性侵", "search_index": 14275, "index": 50}]