[{"index": 1, "keyword": "赵志勇被执行死刑", "search_index": 1093484}, {"index": 2, "keyword": "37岁姚笛近照曝光", "search_index": 1017571}, {"index": 3, "keyword": "主持人贺一航去世", "search_index": 516794}, {"index": 4, "keyword": "林志玲宣布结婚", "search_index": 455768}, {"index": 5, "keyword": "聊天回嗯被批评", "search_index": 451816}, {"index": 6, "keyword": "优衣库联名遭疯抢", "search_index": 432896}, {"index": 7, "keyword": "联想更名联想中国", "search_index": 396178}, {"index": 8, "keyword": "校长表白毕业生", "search_index": 356892}, {"index": 9, "keyword": "护士谋杀85名病人", "search_index": 332803}, {"index": 10, "keyword": "李荣浩发4次祝福", "search_index": 298016}, {"index": 11, "keyword": "华为出售海底光缆", "search_index": 264768}, {"index": 12, "keyword": "文言文写钢铁侠传", "search_index": 258611}, {"index": 13, "keyword": "女孩做鸟用尿不湿", "search_index": 229681}, {"index": 14, "keyword": "章莹颖失踪案开庭", "search_index": 223469}, {"index": 15, "keyword": "丝芙兰全美关店", "search_index": 222713}, {"index": 16, "keyword": "微信部分功能故障", "search_index": 221673}, {"index": 17, "keyword": "秦岚冻龄靠医美", "search_index": 215951}, {"index": 18, "keyword": "内马尔无缘美洲杯", "search_index": 207504}, {"index": 19, "keyword": "内马尔宾馆视频", "search_index": 206873}, {"index": 20, "keyword": "刘诗诗儿子正面照", "search_index": 203678}, {"index": 21, "keyword": "男童校车内离世", "search_index": 187828}, {"index": 22, "keyword": "女子闺蜜同时失踪", "search_index": 181265}, {"index": 23, "keyword": "言承旭祝福林志玲", "search_index": 180557}, {"index": 24, "keyword": "刘涛姚晨同框", "search_index": 179809}, {"index": 25, "keyword": "联邦快递蒸发87亿", "search_index": 178830}, {"index": 26, "keyword": "高考意外提前避坑", "search_index": 174290}, {"index": 27, "keyword": "行拘拟降至14岁", "search_index": 171245}, {"index": 28, "keyword": "中国邮政华为合作", "search_index": 169902}, {"index": 29, "keyword": "郎朗婚宴四手联弹", "search_index": 166274}, {"index": 30, "keyword": "硬核奶奶重返蓝天", "search_index": 165513}, {"index": 31, "keyword": "男子被蚊子咬报警", "search_index": 165230}, {"index": 32, "keyword": "中俄关系新定位", "search_index": 156415}, {"index": 33, "keyword": "第一号留学预警", "search_index": 153981}, {"index": 34, "keyword": "汕头申报自贸区", "search_index": 142895}, {"index": 35, "keyword": "小米股价暴跌", "search_index": 136095}, {"index": 36, "keyword": "破冰行动导演道歉", "search_index": 135953}, {"index": 37, "keyword": "罚写文言文悔过书", "search_index": 132822}, {"index": 38, "keyword": "007片场发生爆炸", "search_index": 132273}, {"index": 39, "keyword": "冯绍峰赵丽颖现身", "search_index": 130519}, {"index": 40, "keyword": "主播遭人酒瓶砸头", "search_index": 124206}, {"index": 41, "keyword": "圈养大熊猫出生", "search_index": 123582}, {"index": 42, "keyword": "沙溢回应培训代言", "search_index": 123130}, {"index": 43, "keyword": "长安福特回应被罚", "search_index": 123051}, {"index": 44, "keyword": "西班牙人教练离任", "search_index": 120643}, {"index": 45, "keyword": "五代168口同堂", "search_index": 117620}, {"index": 46, "keyword": "清华硕士偷拍女性", "search_index": 116238}, {"index": 47, "keyword": "神志不清身藏16万", "search_index": 115787}, {"index": 48, "keyword": "九州缥缈录延播", "search_index": 113209}, {"index": 49, "keyword": "布兰妮信件被公开", "search_index": 110012}, {"index": 50, "keyword": "郭栋楠抄袭致歉", "search_index": 109645}]