[{"index": 1, "keyword": "中国队被取消成绩", "search_index": 185282}, {"index": 2, "keyword": "亚运首例兴奋剂", "search_index": 118874}, {"index": 3, "keyword": "巴神拒绝天价合同", "search_index": 74775}, {"index": 4, "keyword": "金软景 朱婷", "search_index": 37201}, {"index": 5, "keyword": "王倩夺冠", "search_index": 24073}, {"index": 6, "keyword": "丘索维金获银牌", "search_index": 15533}, {"index": 7, "keyword": "kpl转会", "search_index": 14206}, {"index": 8, "keyword": "国乒被淘汰遭禁赛", "search_index": 9955}, {"index": 9, "keyword": "徐嘉余仰泳冠军", "search_index": 9233}, {"index": 10, "keyword": "闻人云涛爆冷出局", "search_index": 7790}, {"index": 11, "keyword": "中超直播", "search_index": 6801}, {"index": 12, "keyword": "上海马拉松", "search_index": 6794}, {"index": 13, "keyword": "中超", "search_index": 6386}, {"index": 14, "keyword": "王珊珊进9球", "search_index": 5808}, {"index": 15, "keyword": "黄紫昌领衔国足", "search_index": 5399}, {"index": 16, "keyword": "中韩游泳选手冲突", "search_index": 4976}, {"index": 17, "keyword": "邓书弟吊环金牌", "search_index": 4177}, {"index": 18, "keyword": "英超直播", "search_index": 3857}, {"index": 19, "keyword": "龙静雯 不公判罚", "search_index": 3808}, {"index": 20, "keyword": "孙杨要求重升国旗", "search_index": 3622}, {"index": 21, "keyword": "英超", "search_index": 2976}, {"index": 22, "keyword": "亚运会金牌榜", "search_index": 2619}, {"index": 23, "keyword": "詹姆斯中国行", "search_index": 2351}, {"index": 24, "keyword": "亚运男足", "search_index": 1984}, {"index": 25, "keyword": "傅园慧无缘奖牌", "search_index": 1877}, {"index": 26, "keyword": "中国林超攀夺冠", "search_index": 1841}, {"index": 27, "keyword": "北京国安", "search_index": 1825}, {"index": 28, "keyword": "西甲", "search_index": 1807}, {"index": 29, "keyword": "日男篮球员被遣返", "search_index": 1789}, {"index": 30, "keyword": "国足小组全胜出线", "search_index": 1694}, {"index": 31, "keyword": "国足vs沙特首发", "search_index": 1625}, {"index": 32, "keyword": "赵若竹夺冠", "search_index": 1537}, {"index": 33, "keyword": "中国男篮", "search_index": 1480}, {"index": 34, "keyword": "姚明指导王哲林", "search_index": 1450}, {"index": 35, "keyword": "西甲直播", "search_index": 1375}, {"index": 36, "keyword": "国乒将出重磅消息", "search_index": 1317}, {"index": 37, "keyword": "意甲", "search_index": 1240}, {"index": 38, "keyword": "孙杨回应风波", "search_index": 1114}, {"index": 39, "keyword": "中国女足2-0朝鲜", "search_index": 1030}, {"index": 40, "keyword": "恒大战鲁能海报", "search_index": 997}, {"index": 41, "keyword": "世界杯直播", "search_index": 995}, {"index": 42, "keyword": "首钢独行侠季前赛", "search_index": 993}, {"index": 43, "keyword": "王蔷女网夺冠", "search_index": 991}, {"index": 44, "keyword": "孙杨1500米决赛视频", "search_index": 989}, {"index": 45, "keyword": "北京马拉松", "search_index": 989}, {"index": 46, "keyword": "中国vs沙特", "search_index": 984}, {"index": 47, "keyword": "中国体操女团冠军", "search_index": 971}, {"index": 48, "keyword": "意甲直播", "search_index": 967}, {"index": 49, "keyword": "德甲", "search_index": 941}, {"index": 50, "keyword": "陈一乐夺冠", "search_index": 937}]