[{"search_index": 174256, "keyword": "心疼假笑男孩", "index": 1}, {"search_index": 122615, "keyword": "副市长身兼46职", "index": 2}, {"search_index": 74086, "keyword": "海底捞淫秽视频案", "index": 3}, {"search_index": 39302, "keyword": "64岁研究员杀妻", "index": 4}, {"search_index": 36996, "keyword": "45年前130元存单", "index": 5}, {"search_index": 34345, "keyword": "阿尔卑斯山区雪崩", "index": 6}, {"search_index": 31050, "keyword": "发小偷光结婚首饰", "index": 7}, {"search_index": 30830, "keyword": "叫停成人门诊输液", "index": 8}, {"search_index": 29589, "keyword": "河北廊坊交通事故", "index": 9}, {"search_index": 28188, "keyword": "数学家阿蒂亚去世", "index": 10}, {"search_index": 26766, "keyword": "广州放松户籍政策", "index": 11}, {"search_index": 23288, "keyword": "巴黎爆炸致20人受伤", "index": 12}, {"search_index": 22643, "keyword": "渥太华交通事故", "index": 13}, {"search_index": 17615, "keyword": "河北狮身人面被拆", "index": 14}, {"search_index": 17543, "keyword": "杀妻骗保泰国结案", "index": 15}, {"search_index": 15422, "keyword": "兰州青年捐献器官", "index": 16}, {"search_index": 15152, "keyword": "跨国抓191名嫌犯", "index": 17}, {"search_index": 14751, "keyword": "暴雪娱乐网易续签", "index": 18}, {"search_index": 14329, "keyword": "小汽车保有量2亿", "index": 19}, {"search_index": 13637, "keyword": "副校长出轨女生", "index": 20}, {"search_index": 13059, "keyword": "泰州干部13岁工作", "index": 21}, {"search_index": 12435, "keyword": "为躲催婚春节值班", "index": 22}, {"search_index": 12128, "keyword": "日本政府算错账", "index": 23}, {"search_index": 11119, "keyword": "替跑消防员致歉", "index": 24}, {"search_index": 7805, "keyword": "充气娃娃漏气报警", "index": 25}, {"search_index": 7256, "keyword": "韩籍液化气船泄漏", "index": 26}, {"search_index": 6601, "keyword": "腊八", "index": 27}, {"search_index": 5601, "keyword": "月球背面全景图", "index": 28}, {"search_index": 5096, "keyword": "巴黎发生燃气爆炸", "index": 29}, {"search_index": 5079, "keyword": "研考自命题事件", "index": 30}, {"search_index": 5060, "keyword": "金湖县过期疫苗", "index": 31}, {"search_index": 4792, "keyword": "男子倒车碾死自己", "index": 32}, {"search_index": 4789, "keyword": "男子炒作辱骂辅警", "index": 33}, {"search_index": 4710, "keyword": "女生元旦宿舍自缢", "index": 34}, {"search_index": 4705, "keyword": "男子失恋烧钱", "index": 35}, {"search_index": 4409, "keyword": "中国游客泰国自杀", "index": 36}, {"search_index": 3844, "keyword": "德鲁大叔", "index": 37}, {"search_index": 3526, "keyword": "北京政府迁址通州", "index": 38}, {"search_index": 3372, "keyword": "杭州奔驰失控开庭", "index": 39}, {"search_index": 3324, "keyword": "韩国的哥自杀", "index": 40}, {"search_index": 2886, "keyword": "南京加油站闪爆", "index": 41}, {"search_index": 2856, "keyword": "近期公布人口数据", "index": 42}, {"search_index": 2854, "keyword": "广州惠州楼房倒塌", "index": 43}, {"search_index": 2808, "keyword": "美金对人民币的汇率", "index": 44}, {"search_index": 2669, "keyword": "新疆阿克苏地震", "index": 45}, {"search_index": 2633, "keyword": "作弊被赶反得高分", "index": 46}, {"search_index": 2556, "keyword": "老挝移交诈骗犯", "index": 47}, {"search_index": 2423, "keyword": "张扣扣一审死刑", "index": 48}, {"search_index": 2308, "keyword": "管道脱落砸私家车", "index": 49}, {"search_index": 2245, "keyword": "美政府停摆20天", "index": 50}]