[{"search_index": 185878, "keyword": "三全回应猪瘟病毒", "index": 1}, {"search_index": 160966, "keyword": "父亲婆婆登记结婚", "index": 2}, {"search_index": 155681, "keyword": "见义勇为反被拘", "index": 3}, {"search_index": 116236, "keyword": "猪坚强12岁", "index": 4}, {"search_index": 116106, "keyword": "玉树发生雪灾", "index": 5}, {"search_index": 115542, "keyword": "家长进游戏群控诉", "index": 6}, {"search_index": 115130, "keyword": "故宫首次晚间开放", "index": 7}, {"search_index": 107780, "keyword": "法院叫停西瓜视频", "index": 8}, {"search_index": 104234, "keyword": "故宫网站崩了", "index": 9}, {"search_index": 103976, "keyword": "立案侦查网贷平台", "index": 10}, {"search_index": 101272, "keyword": "故宫元宵灯会", "index": 11}, {"search_index": 99918, "keyword": "狮航客机滑出跑道", "index": 12}, {"search_index": 98158, "keyword": "印度高铁故障", "index": 13}, {"search_index": 92777, "keyword": "河北定州交通事故", "index": 14}, {"search_index": 76453, "keyword": "误艺考生妈妈痛哭", "index": 15}, {"search_index": 71457, "keyword": "河南发生纵火案", "index": 16}, {"search_index": 69234, "keyword": "英伦航空倒闭", "index": 17}, {"search_index": 62866, "keyword": "西安公司员工失联", "index": 18}, {"search_index": 54654, "keyword": "马克思墓地被毁", "index": 19}, {"search_index": 51655, "keyword": "祭拜先人墓碑垮塌", "index": 20}, {"search_index": 49794, "keyword": "澳男子遇鲨鱼袭击", "index": 21}, {"search_index": 46231, "keyword": "男孩牵手失明母亲", "index": 22}, {"search_index": 45828, "keyword": "烟台回应广告牌", "index": 23}, {"search_index": 36037, "keyword": "民房倒塌房东被拘", "index": 24}, {"search_index": 35823, "keyword": "游戏直播首个禁令", "index": 25}, {"search_index": 35076, "keyword": "军功章被盗扔河里", "index": 26}, {"search_index": 33871, "keyword": "短袖哥勇救男童", "index": 27}, {"search_index": 30140, "keyword": "西安宾利撞出租车", "index": 28}, {"search_index": 29677, "keyword": "城管找到寒假作业", "index": 29}, {"search_index": 27365, "keyword": "警方回应见义勇为", "index": 30}, {"search_index": 25896, "keyword": "发现远古鸭嘴兽龙", "index": 31}, {"search_index": 24138, "keyword": "普京撂倒柔道冠军", "index": 32}, {"search_index": 23680, "keyword": "救护车高速被堵", "index": 33}, {"search_index": 23620, "keyword": "嫌疑犯冯学华落网", "index": 34}, {"search_index": 21679, "keyword": "院长篡改考生成绩", "index": 35}, {"search_index": 18023, "keyword": "石家庄别墅问题", "index": 36}, {"search_index": 17672, "keyword": "咖啡店拍照被收费", "index": 37}, {"search_index": 14264, "keyword": "浙传人性化补考", "index": 38}, {"search_index": 11511, "keyword": "印度呼吁禁止抖音", "index": 39}, {"search_index": 8786, "keyword": "尼日利亚大选推迟", "index": 40}, {"search_index": 8454, "keyword": "美国奥罗拉枪击", "index": 41}, {"search_index": 8094, "keyword": "研究生招生信息网", "index": 42}, {"search_index": 6288, "keyword": "社保", "index": 43}, {"search_index": 6244, "keyword": "美金对人民币的汇率", "index": 44}, {"search_index": 5037, "keyword": "人民币兑美元", "index": 45}, {"search_index": 5016, "keyword": "烟花求婚引火灾", "index": 46}, {"search_index": 4477, "keyword": "鳄雀鳝", "index": 47}, {"search_index": 4085, "keyword": "中国银行外汇牌价", "index": 48}, {"search_index": 3972, "keyword": "感动中国", "index": 49}, {"search_index": 3320, "keyword": "北京社保", "index": 50}]