[{"index": 1, "search_index": 58290, "keyword": "张国伟回应被开除"}, {"index": 2, "search_index": 46735, "keyword": "刘炜最后一场比赛"}, {"index": 3, "search_index": 34222, "keyword": "石原里美传递大使"}, {"index": 4, "search_index": 16717, "keyword": "篮网28分逆转国王"}, {"index": 5, "search_index": 14113, "keyword": "张国伟被曝遭开除"}, {"index": 6, "search_index": 12212, "keyword": "东京奥运火炬设计"}, {"index": 7, "search_index": 8989, "keyword": "edg赢blg"}, {"index": 8, "search_index": 8161, "keyword": "森林狼4连败"}, {"index": 9, "search_index": 6454, "keyword": "苏亚雷斯 中国杯"}, {"index": 10, "search_index": 6183, "keyword": "火箭单节10三分"}, {"index": 11, "search_index": 5147, "keyword": "北京队晋级八强"}, {"index": 12, "search_index": 4164, "keyword": "杜敬谦去世"}, {"index": 13, "search_index": 3168, "keyword": "欧冠"}, {"index": 14, "search_index": 2009, "keyword": "孙杨悼念杜敬谦"}, {"index": 15, "search_index": 1955, "keyword": "黄大宪被取消成绩"}, {"index": 16, "search_index": 1887, "keyword": "威少自动禁赛一场"}, {"index": 17, "search_index": 1725, "keyword": "西甲"}, {"index": 18, "search_index": 1648, "keyword": "英超"}, {"index": 19, "search_index": 1601, "keyword": "cba直播"}, {"index": 20, "search_index": 1564, "keyword": "英格拉姆手术成功"}, {"index": 21, "search_index": 1507, "keyword": "鲁能战平鹿岛鹿角"}, {"index": 22, "search_index": 1343, "keyword": "中超"}, {"index": 23, "search_index": 1259, "keyword": "北京国安"}, {"index": 24, "search_index": 1252, "keyword": "cba季后赛"}, {"index": 25, "search_index": 1002, "keyword": "蒂姆夺大师赛冠军"}, {"index": 26, "search_index": 970, "keyword": "西班牙人"}, {"index": 27, "search_index": 969, "keyword": "nba历史得分榜"}, {"index": 28, "search_index": 968, "keyword": "欧洲杯"}, {"index": 29, "search_index": 962, "keyword": "欧冠赛程"}, {"index": 30, "search_index": 961, "keyword": "诺维茨基升至第6"}, {"index": 31, "search_index": 960, "keyword": "wcba"}, {"index": 32, "search_index": 960, "keyword": "亚冠"}, {"index": 33, "search_index": 960, "keyword": "篮球世界杯"}, {"index": 34, "search_index": 956, "keyword": "欧洲杯预选赛"}, {"index": 35, "search_index": 955, "keyword": "2023亚洲杯主办权"}, {"index": 36, "search_index": 951, "keyword": "德比"}, {"index": 37, "search_index": 951, "keyword": "詹姆斯绝杀被盖"}, {"index": 38, "search_index": 943, "keyword": "ncaa"}, {"index": 39, "search_index": 921, "keyword": "奥尼尔"}, {"index": 40, "search_index": 918, "keyword": "科比开导杨超越"}, {"index": 41, "search_index": 909, "keyword": "意甲"}, {"index": 42, "search_index": 874, "keyword": "冬奥会"}, {"index": 43, "search_index": 859, "keyword": "武磊穿裆过人"}, {"index": 44, "search_index": 857, "keyword": "母其弥雅"}, {"index": 45, "search_index": 852, "keyword": "约基奇被驱逐"}, {"index": 46, "search_index": 840, "keyword": "wcba总决赛"}, {"index": 47, "search_index": 831, "keyword": "兰州马拉松"}, {"index": 48, "search_index": 800, "keyword": "王治郅"}, {"index": 49, "search_index": 772, "keyword": "逍遥散人"}, {"index": 50, "search_index": 761, "keyword": "范加尔告别足坛"}]