[{"index": 1, "keyword": "英国游客被强奸", "search_index": 1331217}, {"index": 2, "keyword": "阿里 奖励164亿", "search_index": 888719}, {"index": 3, "keyword": "安徽新生刺死室友", "search_index": 834818}, {"index": 4, "keyword": "武汉滴滴群聊曝光", "search_index": 750449}, {"index": 5, "keyword": "子弹短信火爆", "search_index": 723647}, {"index": 6, "keyword": "高铁座霸真实身份", "search_index": 710327}, {"index": 7, "keyword": "00后网友仙人跳", "search_index": 678506}, {"index": 8, "keyword": "滴滴拒绝接受监管", "search_index": 613364}, {"index": 9, "keyword": "田亮被爆实际年龄", "search_index": 596404}, {"index": 10, "keyword": "滴滴回应群调侃", "search_index": 584092}, {"index": 11, "keyword": "烟蒂 灭门惨案", "search_index": 560973}, {"index": 12, "keyword": "滴滴遇害女孩微博", "search_index": 559195}, {"index": 13, "keyword": "油泼面禁止泼油", "search_index": 552435}, {"index": 14, "keyword": "收入最高男演员", "search_index": 504450}, {"index": 15, "keyword": "女孩乘滴滴遇害", "search_index": 502123}, {"index": 16, "keyword": "支付宝推到账撤回", "search_index": 496973}, {"index": 17, "keyword": "国乒被淘汰遭禁赛", "search_index": 494610}, {"index": 18, "keyword": "滴滴3年15起性侵", "search_index": 482252}, {"index": 19, "keyword": "美国取消中国航线", "search_index": 476562}, {"index": 20, "keyword": "滴滴嫌犯全家还贷", "search_index": 459980}, {"index": 21, "keyword": "9岁女孩沉迷抖音", "search_index": 452408}, {"index": 22, "keyword": "美航取消上海航班", "search_index": 441486}, {"index": 23, "keyword": "央视控诉吴谨言", "search_index": 410120}, {"index": 24, "keyword": "毕业生薪酬榜", "search_index": 389888}, {"index": 25, "keyword": "火车又现霸座女", "search_index": 387300}, {"index": 26, "keyword": "杀妻藏尸细节披露", "search_index": 378993}, {"index": 27, "keyword": "高铁座霸男子回应", "search_index": 374711}, {"index": 28, "keyword": "韩国清理红灯区", "search_index": 370525}, {"index": 29, "keyword": "医院被骗百亿", "search_index": 366465}, {"index": 30, "keyword": "杭州小学万元校服", "search_index": 338137}, {"index": 31, "keyword": "李小冉欠50万", "search_index": 336443}, {"index": 32, "keyword": "郑爽公开秀恩爱", "search_index": 325965}, {"index": 33, "keyword": "华为禁入日本市场", "search_index": 315380}, {"index": 34, "keyword": "印度拒绝援助", "search_index": 293605}, {"index": 35, "keyword": "未成年人节目管理", "search_index": 270846}, {"index": 36, "keyword": "周杰伦点赞", "search_index": 267835}, {"index": 37, "keyword": "吴亦凡获赔3万元", "search_index": 264111}, {"index": 38, "keyword": "云南8岁女孩遇害", "search_index": 261650}, {"index": 39, "keyword": "女孩为结婚告父母", "search_index": 261395}, {"index": 40, "keyword": "最美天路垃圾成山", "search_index": 260779}, {"index": 41, "keyword": "重庆滴滴司机死缓", "search_index": 257042}, {"index": 42, "keyword": "易烊千玺封面抄袭", "search_index": 256345}, {"index": 43, "keyword": "老太总收暧昧短信", "search_index": 255049}, {"index": 44, "keyword": "冯绍峰 赵丽颖", "search_index": 247244}, {"index": 45, "keyword": "孙杨痛哭", "search_index": 243176}, {"index": 46, "keyword": "解剖鲫鱼保送清华", "search_index": 236044}, {"index": 47, "keyword": "房租占工资三成", "search_index": 235881}, {"index": 48, "keyword": "江南皮革厂16年", "search_index": 232696}, {"index": 49, "keyword": "中国队被取消成绩", "search_index": 231775}, {"index": 50, "keyword": "眼镜蛇钻老人被窝", "search_index": 226564}]