[{"index": 1, "keyword": "冯绍峰朋友圈晒照", "search_index": 619695}, {"index": 2, "keyword": "言承旭喊话林志玲", "search_index": 312694}, {"index": 3, "keyword": "湖州天价小龙虾", "search_index": 288917}, {"index": 4, "keyword": "三里屯缉毒", "search_index": 258749}, {"index": 5, "keyword": "赵丽颖父母来京", "search_index": 251079}, {"index": 6, "keyword": "阳台挂镜辟邪", "search_index": 240084}, {"index": 7, "keyword": "江歌妈妈起诉刘鑫", "search_index": 236528}, {"index": 8, "keyword": "重阳节", "search_index": 212066}, {"index": 9, "keyword": "男孩爬木雕身亡", "search_index": 150156}, {"index": 10, "keyword": "辟谣厦门楼市限购", "search_index": 128132}, {"index": 11, "keyword": "李荣浩新歌4秒", "search_index": 122606}, {"index": 12, "keyword": "哈佛招生歧视亚裔", "search_index": 107184}, {"index": 13, "keyword": "林更新 王丽坤", "search_index": 101364}, {"index": 14, "keyword": "nba揭幕战", "search_index": 98482}, {"index": 15, "keyword": "袁惟仁脑溢血", "search_index": 95766}, {"index": 16, "keyword": "fw出局", "search_index": 94584}, {"index": 17, "keyword": "侵吞公款打赏主播", "search_index": 89759}, {"index": 18, "keyword": "长春疫苗死者赔偿", "search_index": 88195}, {"index": 19, "keyword": "第三次万米深渊", "search_index": 87503}, {"index": 20, "keyword": "冯德伦舒淇晒照", "search_index": 87470}, {"index": 21, "keyword": "登山队遇雪崩遇难", "search_index": 86114}, {"index": 22, "keyword": "赵丽颖收入过亿", "search_index": 82134}, {"index": 23, "keyword": "巴西绝杀阿根廷", "search_index": 74460}, {"index": 24, "keyword": "东北虎上高速", "search_index": 71555}, {"index": 25, "keyword": "张杰撞脸文根英", "search_index": 68263}, {"index": 26, "keyword": "七国集团发声明", "search_index": 65724}, {"index": 27, "keyword": "兰大殴打医生被拘", "search_index": 65409}, {"index": 28, "keyword": "男子捡苍蝇碰瓷", "search_index": 57278}, {"index": 29, "keyword": "艾玛沃特森恋情", "search_index": 55306}, {"index": 30, "keyword": "张馨予被疑有孕", "search_index": 55005}, {"index": 31, "keyword": "沙特失踪记者死亡", "search_index": 50101}, {"index": 32, "keyword": "自如邻居是逃犯", "search_index": 46212}, {"index": 33, "keyword": "私家侦探偷拍判刑", "search_index": 44660}, {"index": 34, "keyword": "霍金 超级人类", "search_index": 43394}, {"index": 35, "keyword": "马刺裁掉吉诺比利", "search_index": 42751}, {"index": 36, "keyword": "比利时1-1荷兰", "search_index": 40206}, {"index": 37, "keyword": "逃犯当伴郎被带走", "search_index": 38826}, {"index": 38, "keyword": "猫和老鼠真人版", "search_index": 38085}, {"index": 39, "keyword": "中国女排小组第1", "search_index": 31545}, {"index": 40, "keyword": "联合惩戒医闹行为", "search_index": 30614}, {"index": 41, "keyword": "燕郊楼市探访", "search_index": 28987}, {"index": 42, "keyword": "长生狂犬病赔偿", "search_index": 28813}, {"index": 43, "keyword": "大学生被精神病", "search_index": 27738}, {"index": 44, "keyword": "全国企业信用信息公示系统", "search_index": 26871}, {"index": 45, "keyword": "熊黛林产后复出", "search_index": 26839}, {"index": 46, "keyword": "成都地铁持凶伤人", "search_index": 26669}, {"index": 47, "keyword": "摩洛哥火车脱轨", "search_index": 26045}, {"index": 48, "keyword": "小吴王境泽同框", "search_index": 24086}, {"index": 49, "keyword": "妻子的浪漫旅行", "search_index": 20673}, {"index": 50, "keyword": "章莹颖案嫌犯离婚", "search_index": 20037}]